edc_adverse_event/__init__.py
edc_adverse_event/action_items/__init__.py
edc_adverse_event/action_items/ae_followup_action.py
edc_adverse_event/action_items/ae_initial_action.py
edc_adverse_event/action_items/ae_susar_action.py
edc_adverse_event/action_items/ae_tmg_action.py
edc_adverse_event/action_items/death_report_action.py
edc_adverse_event/action_items/death_report_tmg_action.py
edc_adverse_event/action_items/death_report_tmg_second_action.py
edc_adverse_event/action_items/hospitalization_action.py
edc_adverse_event/admin.py
edc_adverse_event/admin_site.py
edc_adverse_event/apps.py
edc_adverse_event/auth_objects.py
edc_adverse_event/auths.py
edc_adverse_event/baker_recipes.py
edc_adverse_event/choices.py
edc_adverse_event/constants.py
edc_adverse_event/dashboard_templates.py
edc_adverse_event/dashboard_urls.py
edc_adverse_event/form_validator_mixins/__init__.py
edc_adverse_event/form_validator_mixins/death_report_form_validator.py
edc_adverse_event/form_validator_mixins/requires_death_report_form_validator_mixin.py
edc_adverse_event/form_validators/__init__.py
edc_adverse_event/form_validators/ae_followup.py
edc_adverse_event/form_validators/ae_initial.py
edc_adverse_event/form_validators/ae_susar.py
edc_adverse_event/form_validators/ae_tmg.py
edc_adverse_event/form_validators/death_report.py
edc_adverse_event/form_validators/death_report_tmg.py
edc_adverse_event/form_validators/hospitalization.py
edc_adverse_event/forms/__init__.py
edc_adverse_event/forms/ae_followup_form.py
edc_adverse_event/forms/ae_initial_form.py
edc_adverse_event/forms/ae_susar_form.py
edc_adverse_event/forms/ae_tmg_form.py
edc_adverse_event/forms/death_report_form.py
edc_adverse_event/forms/death_report_tmg_form.py
edc_adverse_event/forms/death_report_tmg_second_form.py
edc_adverse_event/get_ae_model.py
edc_adverse_event/list_data.py
edc_adverse_event/locale/sw/LC_MESSAGES/django.mo
edc_adverse_event/locale/sw/LC_MESSAGES/django.po
edc_adverse_event/middleware.py
edc_adverse_event-1.1.2.dist-info/licenses/LICENSE
edc_adverse_event-1.1.2.dist-info/WHEEL
edc_adverse_event-1.1.2.dist-info/METADATA
edc_adverse_event-1.1.2.dist-info/RECORD
